smartcal/__init__.py
smartcal/bayesian_optimization/__init__.py
smartcal/bayesian_optimization/bayesian_hyperparameters.py
smartcal/bayesian_optimization/calibrators_bayesian_optimization.py
smartcal/calibration_algorithms/__init__.py
smartcal/calibration_algorithms/adaptive_temperature_scaling.py
smartcal/calibration_algorithms/beta.py
smartcal/calibration_algorithms/calibration_base.py
smartcal/calibration_algorithms/dirichlet.py
smartcal/calibration_algorithms/empirical_binning.py
smartcal/calibration_algorithms/isotonic.py
smartcal/calibration_algorithms/matrix_scaling.py
smartcal/calibration_algorithms/meta.py
smartcal/calibration_algorithms/mix_and_match.py
smartcal/calibration_algorithms/probability_tree.py
smartcal/calibration_algorithms/temperature_scaling.py
smartcal/calibration_algorithms/vector_scaling.py
smartcal/calibration_algorithms/histogram/__init__.py
smartcal/calibration_algorithms/histogram/histogram.py
smartcal/calibration_algorithms/histogram/histogram_scaling.py
smartcal/calibration_algorithms/platt/__init__.py
smartcal/calibration_algorithms/platt/platt.py
smartcal/calibration_algorithms/platt/platt_scaling.py
smartcal/calibration_algorithms/platt/platt_scaling_binning.py
smartcal/config/__init__.py
smartcal/config/model_singleton.py
smartcal/config/singleton.py
smartcal/config/configuration_manager/__init__.py
smartcal/config/configuration_manager/configuration_manager.py
smartcal/config/configuration_manager/configuration_manager_base.py
smartcal/config/configuration_manager/configuration_manager_factory.py
smartcal/config/enums/__init__.py
smartcal/config/enums/calibration_algorithms_enum.py
smartcal/config/enums/calibration_error_code_enum.py
smartcal/config/enums/calibration_hyperparameters.py
smartcal/config/enums/calibration_metrics_enum.py
smartcal/config/enums/config_reader_enum.py
smartcal/config/enums/dataset_types_enum.py
smartcal/config/enums/experiment_status_enum.py
smartcal/config/enums/experiment_type_enum.py
smartcal-0.1.16.dist-info/licenses/LICENSE
smartcal-0.1.16.dist-info/METADATA
smartcal-0.1.16.dist-info/WHEEL
smartcal-0.1.16.dist-info/top_level.txt
smartcal-0.1.16.dist-info/RECORD
