Metadata-Version: 2.4
Name: smartcal
Version: 0.1.16
Summary: SmartCal is a modular Python package for auto calibrating machine learning models. It includes multiple calibration algorithms, meta-learning-based method selection, and evaluation metrics. Developed by a team from Giza Systems.
Author-email: Mohamed Maher <m.maher525@gmail.com>, Osama Fayez <osamaoun997@gmail.com>, Youssef Medhat <yossfmedhat@gmail.com>, Mariam Elseedawy <mariam.elseedawy@gmail.com>, Yara Marei <yaramostafa500@gmail.com>, Abdullah Ibrahim <abdullahibrahim544@gmail.com>
Maintainer-email: Mohamed Maher <m.maher525@gmail.com>, Osama Fayez <osamaoun997@gmail.com>, Youssef Medhat <yossfmedhat@gmail.com>, Mariam Elseedawy <mariam.elseedawy@gmail.com>, Yara Marei <yaramostafa500@gmail.com>, Abdullah Ibrahim <abdullahibrahim544@gmail.com>
License: MIT License
Project-URL: Source Code, https://github.com/giza-data-team/SmartCal
Project-URL: Bug Tracker, https://github.com/giza-data-team/SmartCal/issues
Project-URL: Documentation, https://colab.research.google.com/drive/19Tj2z7GfgvQb5Dwjiryg0C0DoieXen2j?usp=sharing
Keywords: auto calibration,automl,machine learning,calibration,meta-learning,uncertainty quantification,probability calibration,model confidence,bayesian optimization
Classifier: Development Status :: 4 - Beta
Classifier: Intended Audience :: Developers
Classifier: Intended Audience :: Science/Research
Classifier: Intended Audience :: Education
Classifier: Topic :: Scientific/Engineering :: Artificial Intelligence
Classifier: Topic :: Scientific/Engineering :: Information Analysis
Classifier: Topic :: Software Development :: Libraries :: Python Modules
Classifier: Programming Language :: Python :: 3
Classifier: Programming Language :: Python :: 3.8
Classifier: Programming Language :: Python :: 3.9
Classifier: Programming Language :: Python :: 3.10
Classifier: Programming Language :: Python :: 3.11
Classifier: Programming Language :: Python :: 3.12
Classifier: License :: OSI Approved :: MIT License
Classifier: Operating System :: OS Independent
Requires-Python: <=3.12,>=3.8
License-File: LICENSE
Requires-Dist: numpy<3.0,>=1.23
Requires-Dist: scipy<2.0,>=1.10
Requires-Dist: pandas<3.0,>=1.5
Requires-Dist: scikit-learn<2.0,>=1.3
Requires-Dist: torch<3.0,>=2.0
Requires-Dist: xgboost<3.0,>=1.7
Requires-Dist: uncertainty-calibration<1.0,>=0.1.3
Requires-Dist: python-decouple
Requires-Dist: betacal
Requires-Dist: bayesian-optimization
Provides-Extra: dev
Requires-Dist: pytest>=8.1.1; extra == "dev"
Requires-Dist: black>=24.3.0; extra == "dev"
Requires-Dist: mypy>=1.9.0; extra == "dev"
Requires-Dist: twine>=5.0.0; extra == "dev"
Requires-Dist: build>=1.2.1; extra == "dev"
Dynamic: license-file
